pointr_cloud_mcp_server/PointrAgent.py
pointr_cloud_mcp_server/__init__.py
pointr_cloud_mcp_server/app.py
pointr_cloud_mcp_server-0.1.0.dist-info/licenses/LICENSE
pointr_cloud_mcp_server-0.1.0.dist-info/METADATA
pointr_cloud_mcp_server-0.1.0.dist-info/WHEEL
pointr_cloud_mcp_server-0.1.0.dist-info/entry_points.txt
pointr_cloud_mcp_server-0.1.0.dist-info/top_level.txt
pointr_cloud_mcp_server-0.1.0.dist-info/RECORD
